django_fast_update-0.3.0.dist-info/licenses/LICENSE.txt
fast_update/__init__.py
fast_update/copy.py
fast_update/fast.py
fast_update/query.py
fast_update/update.py
django_fast_update-0.3.0.dist-info/METADATA
django_fast_update-0.3.0.dist-info/WHEEL
django_fast_update-0.3.0.dist-info/top_level.txt
django_fast_update-0.3.0.dist-info/RECORD
