Metadata-Version: 2.4
Name: django-fast-update
Version: 0.3.0
Summary: Faster db updates for Django using UPDATE FROM VALUES sql variants.
Home-page: https://github.com/netzkolchose/django-fast-update
Download-URL: https://github.com/netzkolchose/django-fast-update/archive/v0.3.0.tar.gz
Author: netzkolchose
Author-email: j.breitbart@netzkolchose.de
License: MIT
Keywords: django,bulk_update,fast,update,fast_update
Classifier: Development Status :: 4 - Beta
Classifier: Intended Audience :: Developers
Classifier: Topic :: Database
Classifier: Topic :: Database :: Front-Ends
Classifier: Topic :: Software Development :: Libraries
Classifier: Framework :: Django
Classifier: Framework :: Django :: 4.2
Classifier: Framework :: Django :: 5.2
Classifier: License :: OSI Approved :: MIT License
Classifier: Programming Language :: Python :: 3
Classifier: Programming Language :: Python :: 3.11
Classifier: Programming Language :: Python :: 3.12
Classifier: Programming Language :: Python :: 3.13
License-File: LICENSE.txt
Requires-Dist: Django>=4.2
Dynamic: author
Dynamic: author-email
Dynamic: classifier
Dynamic: description
Dynamic: description-content-type
Dynamic: download-url
Dynamic: home-page
Dynamic: keywords
Dynamic: license
Dynamic: license-file
Dynamic: requires-dist
Dynamic: summary
